earthkit/transforms/__init__.py
earthkit/transforms/_aggregate.py
earthkit/transforms/_tools.py
earthkit/transforms/version.py
earthkit/transforms/aggregate/__init__.py
earthkit/transforms/aggregate/_deprecate.py
earthkit/transforms/aggregate/climatology.py
earthkit/transforms/aggregate/ensemble.py
earthkit/transforms/aggregate/general.py
earthkit/transforms/aggregate/spatial.py
earthkit/transforms/aggregate/temporal.py
earthkit/transforms/climatology/__init__.py
earthkit/transforms/climatology/_aggregate.py
earthkit/transforms/ensemble/__init__.py
earthkit/transforms/ensemble/_aggregate.py
earthkit/transforms/spatial/__init__.py
earthkit/transforms/spatial/_aggregate.py
earthkit/transforms/temporal/__init__.py
earthkit/transforms/temporal/_aggregate.py
earthkit_transforms-0.5.3.dist-info/licenses/LICENSE
earthkit_transforms-0.5.3.dist-info/METADATA
earthkit_transforms-0.5.3.dist-info/WHEEL
earthkit_transforms-0.5.3.dist-info/top_level.txt
earthkit_transforms-0.5.3.dist-info/RECORD
