Metadata-Version: 2.4
Name: earthkit-transforms
Version: 0.5.3
Summary: Aggregation tools for meteorological and climate data.
License-Expression: Apache-2.0
Classifier: Development Status :: 4 - Beta
Classifier: Intended Audience :: Science/Research
Classifier: Operating System :: OS Independent
Classifier: Programming Language :: Python
Classifier: Programming Language :: Python :: 3
Classifier: Programming Language :: Python :: 3.10
Classifier: Topic :: Scientific/Engineering
License-File: LICENSE
Requires-Dist: array-api-compat
Requires-Dist: xarray>=2022.3.0
Requires-Dist: numpy>=1.18
Requires-Dist: earthkit-data>=0.11.2
Requires-Dist: earthkit-utils
Requires-Dist: geopandas
Provides-Extra: all
Requires-Dist: rasterio; extra == "all"
Provides-Extra: rasterio
Requires-Dist: rasterio; extra == "rasterio"
Dynamic: license-file
